rest_framework_role_filters/__init__.py
rest_framework_role_filters/mixins.py
rest_framework_role_filters/role_filters.py
rest_framework_role_filters/viewsets.py
djangorestframework_role_filters-1.1.0.dist-info/LICENSE
djangorestframework_role_filters-1.1.0.dist-info/METADATA
djangorestframework_role_filters-1.1.0.dist-info/WHEEL
djangorestframework_role_filters-1.1.0.dist-info/top_level.txt
djangorestframework_role_filters-1.1.0.dist-info/RECORD
