Metadata-Version: 2.1
Name: djangorestframework-role-filters
Version: 1.1.0
Summary: django-rest-framework-role-filters
Home-page: https://github.com/allisson/django-rest-framework-role-filters
Author: Allisson Azevedo
Author-email: allisson@gmail.com
Keywords: djangorestframework rest role permission
Classifier: Development Status :: 5 - Production/Stable
Classifier: Environment :: Web Environment
Classifier: Framework :: Django
Classifier: Intended Audience :: Developers
Classifier: License :: OSI Approved :: MIT License
Classifier: Operating System :: OS Independent
Classifier: Programming Language :: Python :: 3.8
Classifier: Programming Language :: Python :: 3.9
Classifier: Programming Language :: Python :: 3.10
Classifier: Programming Language :: Python :: 3.11
Classifier: Programming Language :: Python :: 3.12
Classifier: Topic :: Internet :: WWW/HTTP
Classifier: Topic :: Software Development :: Libraries :: Application Frameworks
Classifier: Topic :: Software Development :: Libraries :: Python Modules
License-File: LICENSE
Requires-Dist: djangorestframework >=3.10.3
